{
  "url": "https://le-cook.sznm.dev/",
  "requestedUrl": "https://le-cook.sznm.dev/",
  "timestamp": 1606265247890,
  "ranks": {
    "hundos": 5,
    "performance": 4,
    "accessibility": 6,
    "cumulative": 5
  },
  "lighthouse": {
    "version": "6.4.1",
    "performance": 0.73,
    "accessibility": 0.78,
    "bestPractices": 0.93,
    "seo": 0.92,
    "total": 336
  },
  "firstContentfulPaint": 1219.733,
  "speedIndex": 1888.1558165347046,
  "largestContentfulPaint": 1369.733,
  "totalBlockingTime": 1575.5000000000002,
  "cumulativeLayoutShift": 0,
  "timeToInteractive": 4914.0465,
  "maxPotentialFirstInputDelay": 714.0000000000002,
  "timeToFirstByte": 24.967000000000006,
  "weight": {
    "summary": "30 requests • 306 KiB",
    "total": 313731,
    "image": 29782,
    "imageCount": 11,
    "script": 274076,
    "scriptCount": 6,
    "document": 7812,
    "font": 0,
    "fontCount": 0,
    "stylesheet": 0,
    "stylesheetCount": 0,
    "thirdParty": 1549,
    "thirdPartyCount": 11
  },
  "axe": {
    "passes": 278,
    "violations": 15
  }
}