{
  "url": "https://agustinusnathaniel.com/",
  "requestedUrl": "https://agustinusnathaniel.com/",
  "timestamp": 1608684207889,
  "ranks": {
    "hundos": 2,
    "performance": 6,
    "accessibility": 1,
    "cumulative": 3
  },
  "lighthouse": {
    "version": "6.5.0",
    "performance": 0.86,
    "accessibility": 0.98,
    "bestPractices": 0.93,
    "seo": 0.98,
    "total": 375
  },
  "firstContentfulPaint": 1162.4250000000002,
  "speedIndex": 3657.4030331855874,
  "largestContentfulPaint": 2050.623,
  "totalBlockingTime": 404,
  "cumulativeLayoutShift": 0.0023840196397569443,
  "timeToInteractive": 6115.1230000000005,
  "maxPotentialFirstInputDelay": 318,
  "timeToFirstByte": 65.24000000000001,
  "weight": {
    "summary": "50 requests • 772 KiB",
    "total": 790484,
    "image": 53025,
    "imageCount": 1,
    "script": 632631,
    "scriptCount": 10,
    "document": 10443,
    "font": 88398,
    "fontCount": 4,
    "stylesheet": 0,
    "stylesheetCount": 0,
    "thirdParty": 461792,
    "thirdPartyCount": 6
  },
  "run": {
    "number": 2,
    "total": 3
  },
  "axe": {
    "passes": 139,
    "violations": 11
  }
}