{
  "url": "https://sznm.dev/",
  "requestedUrl": "https://sznm.dev/",
  "timestamp": 1711930047818,
  "ranks": {
    "hundos": 5,
    "performance": 10,
    "accessibility": 5,
    "cumulative": 5
  },
  "lighthouse": {
    "version": "11.7.0",
    "performance": 0.87,
    "accessibility": 0.99,
    "bestPractices": 0.93,
    "seo": 1,
    "total": 379
  },
  "firstContentfulPaint": 1837.484,
  "firstMeaningfulPaint": 1837.484,
  "speedIndex": 3330.0161172270714,
  "largestContentfulPaint": 3487.484,
  "totalBlockingTime": 171,
  "cumulativeLayoutShift": 0,
  "timeToInteractive": 4111.484,
  "maxPotentialFirstInputDelay": 150,
  "timeToFirstByte": 324.123,
  "weight": {
    "summary": "48 requests • 540.3 KiB",
    "total": 553273,
    "image": 78537,
    "imageCount": 4,
    "script": 364877,
    "scriptCount": 30,
    "document": 21635,
    "font": 58804,
    "fontCount": 2,
    "stylesheet": 1235,
    "stylesheetCount": 1,
    "thirdParty": 0,
    "thirdPartyCount": 1
  },
  "run": {
    "number": 1,
    "total": 1
  },
  "sidequests": {
    "-weight.total": 6,
    "+weight.total": 6,
    "-weight.document": 7,
    "+weight.document": 5,
    "-weight.script": 7,
    "+weight.script": 5,
    "-weight.image": 4,
    "+weight.image": 2,
    "-weight.font": 5,
    "+weight.font": 7,
    "+weight.fontCount": 4,
    "-timeToFirstByte": 11,
    "-totalBlockingTime": 9,
    "-largestContentfulPaint": 10
  },
  "axe": {
    "passes": 436,
    "violations": 10
  }
}