{
  "url": "https://sveltekit-tw.sznm.dev/",
  "requestedUrl": "https://sveltekit-tw.sznm.dev/",
  "timestamp": 1672065575303,
  "ranks": {
    "hundos": 11,
    "performance": 3,
    "accessibility": 11,
    "cumulative": 11
  },
  "lighthouse": {
    "version": "9.6.8",
    "performance": 1,
    "accessibility": 0.96,
    "bestPractices": 0.92,
    "seo": 0.92,
    "total": 380
  },
  "firstContentfulPaint": 1206.516,
  "firstMeaningfulPaint": 1206.516,
  "speedIndex": 1470.4270479998718,
  "largestContentfulPaint": 1206.516,
  "totalBlockingTime": 0,
  "cumulativeLayoutShift": 0.002115898980034722,
  "timeToInteractive": 1206.516,
  "maxPotentialFirstInputDelay": 16,
  "timeToFirstByte": 542.2620000000001,
  "weight": {
    "summary": "11 requests • 59 KiB",
    "total": 60124,
    "image": 910,
    "imageCount": 1,
    "script": 22575,
    "scriptCount": 5,
    "document": 1532,
    "font": 32637,
    "fontCount": 3,
    "stylesheet": 2470,
    "stylesheetCount": 1,
    "thirdParty": 910,
    "thirdPartyCount": 1
  },
  "run": {
    "number": 1,
    "total": 1
  },
  "sidequests": {
    "-weight.total": 1,
    "+weight.total": 12,
    "-weight.document": 5,
    "+weight.document": 8,
    "-weight.script": 3,
    "+weight.script": 10,
    "-weight.image": 2,
    "+weight.image": 10,
    "-weight.font": 7,
    "+weight.font": 6,
    "+weight.fontCount": 1,
    "-timeToFirstByte": 9,
    "-totalBlockingTime": 1,
    "-largestContentfulPaint": 3
  },
  "axe": {
    "passes": 47,
    "violations": 1
  }
}